arcor2_3d_mouse/VERSION
arcor2_3d_mouse/__init__.py
arcor2_3d_mouse/mouse_controller.py
arcor2_3d_mouse/mouse_program.py
arcor2_3d_mouse/py.typed
arcor2_3d_mouse/scripts/__init__.py
arcor2_3d_mouse/scripts/mouse_launcher.py
arcor2_3d_mouse-1.1.0.dist-info/METADATA
arcor2_3d_mouse-1.1.0.dist-info/WHEEL
arcor2_3d_mouse-1.1.0.dist-info/entry_points.txt
arcor2_3d_mouse-1.1.0.dist-info/namespace_packages.txt
arcor2_3d_mouse-1.1.0.dist-info/top_level.txt
arcor2_3d_mouse-1.1.0.dist-info/RECORD
