Metadata-Version: 2.1
Name: arcor2-3d-mouse
Version: 1.1.0
Summary: ARCOR2 library for manipulation with 3D mouse
Author: Robo@FIT
Author-email: imaterna@fit.vut.cz
License: LGPL
Classifier: Development Status :: 3 - Alpha
Classifier: Intended Audience :: Developers
Classifier: Topic :: Software Development :: Build Tools
Classifier: License :: OSI Approved :: GNU Lesser General Public License v3 (LGPLv3)
Classifier: Programming Language :: Python :: 3.11
Classifier: Natural Language :: English
Classifier: Topic :: Scientific/Engineering
Requires-Python: ==3.11.*
Requires-Dist: arcor2-arserver-data (~=1.1.0)
Requires-Dist: arcor2-calibration-data (~=1.1.0)
Requires-Dist: arcor2-execution-data (~=1.2.0)
Requires-Dist: arcor2-runtime (~=1.2.0)
Requires-Dist: arcor2 (~=1.3.0)
Requires-Dist: gTTS (~=2.5.1)
Requires-Dist: pydub-stubs (==0.25.1.1)
Requires-Dist: pydub (~=0.25.1)
Requires-Dist: pyspacemouse (~=1.1.1)
